django_slackbot/__init__.py
django_slackbot/apps.py
django_slackbot/chat.py
django_slackbot/tests.py
django_slackbot/app_home/__init__.py
django_slackbot/app_home/apps.py
django_slackbot/app_home/chat.py
django_slackbot/frinkiac/__init__.py
django_slackbot/frinkiac/apps.py
django_slackbot/frinkiac/chat.py
django_slackbot/management/__init__.py
django_slackbot/management/commands/__init__.py
django_slackbot/management/commands/run_scheduler.py
django_slackbot/management/commands/run_slackbot.py
django_bubblehouse_slackbot-1.1.1.dist-info/LICENSE
django_bubblehouse_slackbot-1.1.1.dist-info/METADATA
django_bubblehouse_slackbot-1.1.1.dist-info/WHEEL
django_bubblehouse_slackbot-1.1.1.dist-info/top_level.txt
django_bubblehouse_slackbot-1.1.1.dist-info/RECORD
